mcp_yx_fileinfo/__init__.py
mcp_yx_fileinfo/file_info.py
mcp_yx_fileinfo-0.2.5.dist-info/METADATA
mcp_yx_fileinfo-0.2.5.dist-info/WHEEL
mcp_yx_fileinfo-0.2.5.dist-info/entry_points.txt
mcp_yx_fileinfo-0.2.5.dist-info/RECORD
