Metadata-Version: 2.4
Name: mcp-yx-fileinfo
Version: 0.2.5
Summary: Add your description here
Author-email: 御雪 <wb-spf530106@alibaba-inc.com>
Requires-Python: >=3.10
Requires-Dist: mcp[cli]>=1.7.1
